{
  "web.js": {
    "bundled": 69051,
    "minified": 30978,
    "gzipped": 9326,
    "treeshaked": {
      "rollup": {
        "code": 14013,
        "import_statements": 753
      },
      "webpack": {
        "code": 16540
      }
    }
  },
  "web.cjs.js": {
    "bundled": 88353,
    "minified": 40343,
    "gzipped": 10599
  },
  "vscroll.js": {
    "bundled": 12612,
    "minified": 5447,
    "gzipped": 2205,
    "treeshaked": {
      "rollup": {
        "code": 1496,
        "import_statements": 158
      },
      "webpack": {
        "code": 3013
      }
    }
  },
  "vscroll.cjs.js": {
    "bundled": 15673,
    "minified": 6575,
    "gzipped": 2419
  },
  "scrollbar.js": {
    "bundled": 22594,
    "minified": 9207,
    "gzipped": 3050,
    "treeshaked": {
      "rollup": {
        "code": 1170,
        "import_statements": 112
      },
      "webpack": {
        "code": 2595
      }
    }
  },
  "scrollbar.cjs.js": {
    "bundled": 28285,
    "minified": 12012,
    "gzipped": 3584
  },
  "examples.js": {
    "bundled": 2866,
    "minified": 1792,
    "gzipped": 822,
    "treeshaked": {
      "rollup": {
        "code": 221,
        "import_statements": 221
      },
      "webpack": {
        "code": 1403
      }
    }
  },
  "examples.cjs.js": {
    "bundled": 3788,
    "minified": 2231,
    "gzipped": 973
  },
  "stdlib.js": {
    "bundled": 7905,
    "minified": 3944,
    "gzipped": 1546,
    "treeshaked": {
      "rollup": {
        "code": 168,
        "import_statements": 168
      },
      "webpack": {
        "code": 1317
      }
    }
  },
  "stdlib.cjs.js": {
    "bundled": 11490,
    "minified": 5614,
    "gzipped": 1899
  }
}
